config/__init__.py
config/_registry.py
config/convert.py
config/helpers.py
config/utils.py
cygnet_config-0.0.1.dist-info/LICENSE
cygnet_config-0.0.1.dist-info/METADATA
cygnet_config-0.0.1.dist-info/WHEEL
cygnet_config-0.0.1.dist-info/top_level.txt
cygnet_config-0.0.1.dist-info/RECORD
